ovos_skill_volume/LICENSE
ovos_skill_volume/MANIFEST.in
ovos_skill_volume/README.md
ovos_skill_volume/__init__.py
ovos_skill_volume/version.py
ovos_skill_volume/locale/ca-es/change.voc
ovos_skill_volume/locale/ca-es/current.voc
ovos_skill_volume/locale/ca-es/error.get.volume.dialog
ovos_skill_volume/locale/ca-es/louder.voc
ovos_skill_volume/locale/ca-es/quieter.voc
ovos_skill_volume/locale/ca-es/skill.json
ovos_skill_volume/locale/ca-es/volume.change.amount.dialog
ovos_skill_volume/locale/ca-es/volume.current.dialog
ovos_skill_volume/locale/ca-es/volume.default.intent
ovos_skill_volume/locale/ca-es/volume.high.intent
ovos_skill_volume/locale/ca-es/volume.low.intent
ovos_skill_volume/locale/ca-es/volume.max.already.dialog
ovos_skill_volume/locale/ca-es/volume.max.dialog
ovos_skill_volume/locale/ca-es/volume.max.intent
ovos_skill_volume/locale/ca-es/volume.mute.intent
ovos_skill_volume/locale/ca-es/volume.mute.toggle.intent
ovos_skill_volume/locale/ca-es/volume.set.percent.dialog
ovos_skill_volume/locale/ca-es/volume.unmute.intent
ovos_skill_volume/locale/ca-es/volume.voc
ovos_skill_volume/locale/da-dk/change.voc
ovos_skill_volume/locale/da-dk/current.voc
ovos_skill_volume/locale/da-dk/error.get.volume.dialog
ovos_skill_volume/locale/da-dk/louder.voc
ovos_skill_volume/locale/da-dk/quieter.voc
ovos_skill_volume/locale/da-dk/skill.json
ovos_skill_volume/locale/da-dk/volume.change.amount.dialog
ovos_skill_volume/locale/da-dk/volume.current.dialog
ovos_skill_volume/locale/da-dk/volume.default.intent
ovos_skill_volume/locale/da-dk/volume.high.intent
ovos_skill_volume/locale/da-dk/volume.low.intent
ovos_skill_volume/locale/da-dk/volume.max.already.dialog
ovos_skill_volume/locale/da-dk/volume.max.dialog
ovos_skill_volume/locale/da-dk/volume.max.intent
ovos_skill_volume/locale/da-dk/volume.mute.intent
ovos_skill_volume/locale/da-dk/volume.mute.toggle.intent
ovos_skill_volume/locale/da-dk/volume.set.percent.dialog
ovos_skill_volume/locale/da-dk/volume.unmute.intent
ovos_skill_volume/ovos_skill_volume.egg-info/PKG-INFO
ovos_skill_volume/ovos_skill_volume.egg-info/SOURCES.txt
ovos_skill_volume/ovos_skill_volume.egg-info/dependency_links.txt
ovos_skill_volume/ovos_skill_volume.egg-info/entry_points.txt
ovos_skill_volume/ovos_skill_volume.egg-info/requires.txt
ovos_skill_volume/ovos_skill_volume.egg-info/top_level.txt
ovos_skill_volume-0.1.16.dist-info/LICENSE
ovos_skill_volume-0.1.16.dist-info/METADATA
ovos_skill_volume-0.1.16.dist-info/WHEEL
ovos_skill_volume-0.1.16.dist-info/entry_points.txt
ovos_skill_volume-0.1.16.dist-info/top_level.txt
ovos_skill_volume-0.1.16.dist-info/RECORD
