Metadata-Version: 2.1
Name: ovos-skill-volume
Version: 0.1.16
Summary: ovos skill plugin
Home-page: https://github.com/OpenVoiceOS/ovos-skill-volume
Author: JarbasAi
Author-email: jarbasai@mailfence.com
License: Apache-2.0
Keywords: ovos skill plugin
License-File: LICENSE
Requires-Dist: ovos-utils<1.0.0,>=0.0.38
Requires-Dist: ovos-workshop<8.0.0,>=0.0.15
Requires-Dist: ovos-utterance-normalizer<1.0.0,>=0.0.1
Requires-Dist: ovos-number-parser<1.0.0,>=0.0.1
